Workbook

Sheet Leia-me
B2: PPI — Preço de Paridade de Importação de combustíveis
B3: Reprodução do cálculo + série histórica oficial (ANP), 2016–2026
B5: O que tem nesta pasta de trabalho
B6: • Calculadora PPI — reproduz a fórmula do PPI (cotação internacional + frete, convertido pelo câmbio, mais tributos e custos de internação) de forma editável, célula a célula.
B7: • Brent e Câmbio (2016-2026) — série mensal de referência (Brent, EIA/FRED; USD/BRL, Banco Central) usada como insumo/contexto da calculadora.
B8: • PPI ANP - Diesel / Gasolina (semanal) — o PPI JÁ CALCULADO pela ANP (metodologia S&P Global Commodity Insights / Abicom-StoneX), semanal, por polo de entrega, nov/2018 a set/2026. Isto é o número oficial, não uma reconstrução.
B9: • Preço Realização (semanal) — preço médio ponderado semanal efetivamente praticado pelas refinarias ("preço de realização"), nacional, sem ICMS, para diesel e gasolina, 2016-2026 — fonte ANP.
B10: • Defasagem Histórica (mensal) — cruza os dois acima: PPI médio mensal vs. preço de realização médio mensal = defasagem em %, com gráfico. Esta é a série histórica de fato.
B11: • Fontes — todos os links e datas de extração.
B13: Limitações importantes (leia antes de usar)
B14: 1. Escopo temporal: a política oficial de paridade de importação da Petrobras só existe desde outubro/2016. A ANP só publica o PPI calculado a partir de nov/2018 — por isso a aba de defasagem histórica começa em nov/2018, não em 2016.
B15: 2. Fim da política PPI: em 16/05/2023 a Petrobras anunciou o fim oficial da política de paridade de importação, substituindo-a por "custo alternativo do cliente" e "valor marginal". A série de "preço de realização" da ANP continua sendo publicada normalmente depois disso, mas a comparação deixa de refletir uma política de PPI explícita da Petrobras a partir dessa data — trate os meses após mai/2023 como "defasagem vs. paridade de importação de mercado", não "desvio de uma política que a empresa ainda segue".
... B19: 6. A cotação internacional do produto refinado (gasolina RBOB / diesel ULSD, Platts ou Argus) é diferente do preço do petróleo Brent (cru). Brent está aqui só como referência de contexto — ele não é, tecnicamente, o insumo direto da fórmula do PPI. Cole a cotação do produto refinado na célula amarela da Calculadora quando tiver acesso a ela.

Sheet Calculadora PPI
B2: Calculadora PPI — reprodução manual da fórmula
B3: PPI (R$/L) = ((Cotação internacional do produto ÷ litros por galão) + (Frete ÷ litros por barril)) × Câmbio + Tributos + Custos de internação
B5: Legenda: | C5: azul = você edita | D5: amarelo = premissa sem fonte pública confirmada — preencha com o que você tiver
B6: Insumos
B7: Mês de referência (AAAA-MM) | G7: 2026-08
B8: Cotação internacional do produto (US$/galão) — cole aqui Platts/Argus (RBOB gasolina ou ULSD diesel)
B9: Frete internacional (US$/barril) | G9: 0
B10: Câmbio (R$/US$) — puxe da aba 'Brent e Câmbio' pelo mês acima | G10: =INDEX('Brent e Câmbio'!C:C,MATCH(G7,'Brent e Câmbio'!A:A,0))
B11: Tributos (R$/L) — 0 para comparar na mesma base do PPI/ANP (sem tributos) | G11: 0
B12: Custos de internação / armazenagem / margem do importador (R$/L) | G12: 0
B13: Litros por galão (constante física) | G13: 3.7854118
B14: Litros por barril (constante física) | G14: 158.98729
B15: Preço de venda da Petrobras / refinaria (R$/L) — "preço de realização"
B18: Resultado
B19: PPI calculado (R$/L) | G19: =(G8/G13 + G9/G14)*G10 + G11 + G12
B20: Defasagem = (PPI − Preço Petrobras) ÷ PPI | G20: =IF(G19=0,"",(G19-G15)/G19)
B21: Leitura: defasagem positiva = Petrobras abaixo da paridade de importação ("atrasado"); negativa = Petrobras acima da paridade.

Sheet Brent e Câmbio
A1: Brent (EIA/FRED, MCOILBRENTEU) e Câmbio USD/BRL (BCB SGS 3695) — médias mensais
A2: Mês | B2: Brent (US$/barril) | C2: Câmbio (R$/US$, venda, média mês) | D2: Fonte
A3: 2016-01 | B3: 30.7 | C3: 4.0422 | D3: EIA/FRED (Brent) + BCB SGS 3695 (câmbio)
A4: 2016-02 | B4: 32.18 | C4: 3.979 | D4: EIA/FRED (Brent) + BCB SGS 3695 (câmbio)
A5: 2016-03 | B5: 38.21 | C5: 3.5583 | D5: EIA/FRED (Brent) + BCB SGS 3695 (câmbio)
A6: 2016-04 | B6: 41.58 | C6: 3.4502 | D6: EIA/FRED (Brent) + BCB SGS 3695 (câmbio)
A7: 2016-05 | B7: 46.74 | C7: 3.5945 | D7: EIA/FRED (Brent) + BCB SGS 3695 (câmbio)
A8: 2016-06 | B8: 48.25 | C8: 3.2092 | D8: EIA/FRED (Brent) + BCB SGS 3695 (câmbio)
A9: 2016-07 | B9: 44.95 | C9: 3.2384 | D9: EIA/FRED (Brent) + BCB SGS 3695 (câmbio)
A10: 2016-08 | B10: 45.84 | C10: 3.2397 | D10: EIA/FRED (Brent) + BCB SGS 3695 (câmbio)
A11: 2016-09 | B11: 46.57 | C11: 3.2456 | D11: EIA/FRED (Brent) + BCB SGS 3695 (câmbio)
A12: 2016-10 | B12: 49.52 | C12: 3.1805 | D12: EIA/FRED (Brent) + BCB SGS 3695 (câmbio)
A13: 2016-11 | B13: 44.73 | C13: 3.3961 | D13: EIA/FRED (Brent) + BCB SGS 3695 (câmbio)
A14: 2016-12 | B14: 53.31 | C14: 3.2585 | D14: EIA/FRED (Brent) + BCB SGS 3695 (câmbio)
... A130: 2026-08 | B130: 91.08 | C130: 5.181 | D130: EIA/FRED (Brent) + BCB SGS 3695 (câmbio)
A131: 2026-09 (parcial) | D131: Mês ainda não fechado em 28/09/2026 — câmbio diário oscilando entre R$5,09 e R$5,22 (BCB SGS 1); Brent só disponível como média mensal em out/2026

Sheet PPI ANP - Diesel (semanal)
A1: PPI oficial ANP — Diesel (semanal) — médio semanal por polo (R$/litro, sem tributos)
A2: Semana início | B2: Semana fim | C2: AnoMes | D2: Manaus | E2: Itaqui | F2: Suape | G2: Aratu | H2: Santos | I2: Paranagua | J2: Tramandai | K2: Guamare | L2: Duque de Caxias | M2: Betim | N2: Cubatao | O2: Maua | P2: Paulinia | Q2: Sao Jose dos Campos | R2: Araucaria | S2: Canoas | T2: Média simples (aprox. nacional)
A3: 43409 | B3: 43413 | C3: =TEXT(A3,"yyyy-mm") | E3: 2.249686 | F3: 2.2504 | G3: 2.264426 | H3: 2.299988 | I3: 2.28141 | T3: =IFERROR(AVERAGE(D3:S3),"")
A4: 43416 | B4: 43420 | C4: =TEXT(A4,"yyyy-mm") | E4: 2.159192 | F4: 2.160458 | G4: 2.174492 | H4: 2.210074 | I4: 2.191472 | T4: =IFERROR(AVERAGE(D4:S4),"")
A5: 43421 | B5: 43425 | C5: =TEXT(A5,"yyyy-mm") | E5: 2.1038633 | F5: 2.1029167 | G5: 2.1191667 | H5: 2.1584 | I5: 2.1408367 | T5: =IFERROR(AVERAGE(D5:S5),"")
A6: 43430 | B6: 43434 | C6: =TEXT(A6,"yyyy-mm") | E6: 1.990058 | F6: 1.988348 | G6: 2.005388 | H6: 2.045942 | I6: 2.028652 | T6: =IFERROR(AVERAGE(D6:S6),"")
A7: 43437 | B7: 43441 | C7: =TEXT(A7,"yyyy-mm") | E7: 1.9939 | F7: 1.9885 | G7: 2.0092 | H7: 2.0559 | I7: 2.0404 | T7: =IFERROR(AVERAGE(D7:S7),"")
A8: 43444 | B8: 43448 | C8: =TEXT(A8,"yyyy-mm") | E8: 1.9817 | F8: 1.9759 | G8: 1.997 | H8: 2.0443 | I8: 2.0289 | T8: =IFERROR(AVERAGE(D8:S8),"")
A9: 43451 | B9: 43455 | C9: =TEXT(A9,"yyyy-mm") | E9: 1.874776 | F9: 1.87347 | G9: 1.890108 | H9: 1.929994 | I9: 1.912502 | T9: =IFERROR(AVERAGE(D9:S9),"")
A10: 43458 | B10: 43462 | C10: =TEXT(A10,"yyyy-mm") | E10: 1.7468125 | F10: 1.7696603 | G10: 1.7772878 | H10: 1.7979463 | I10: 1.7782319 | T10: =IFERROR(AVERAGE(D10:S10),"")
A11: 43465 | B11: 43469 | C11: =TEXT(A11,"yyyy-mm") | E11: 1.71951 | F11: 1.7216367 | G11: 1.73471 | H11: 1.7704367 | I11: 1.7521567 | T11: =IFERROR(AVERAGE(D11:S11),"")
A12: 43472 | B12: 43476 | C12: =TEXT(A12,"yyyy-mm") | E12: 1.811598 | F12: 1.814008 | G12: 1.82678 | H12: 1.860204 | I12: 1.841488 | T12: =IFERROR(AVERAGE(D12:S12),"")
A13: 43479 | B13: 43483 | C13: =TEXT(A13,"yyyy-mm") | E13: 1.883856 | F13: 1.887634 | G13: 1.89903 | H13: 1.930178 | I13: 1.910842 | T13: =IFERROR(AVERAGE(D13:S13),"")
A14: 43486 | B14: 43490 | C14: =TEXT(A14,"yyyy-mm") | E14: 1.93559 | F14: 1.9397975 | G14: 1.9507675 | H14: 1.98121 | I14: 1.9616725 | T14: =IFERROR(AVERAGE(D14:S14),"")
... A45: 43703 | B45: 43707 | C45: =TEXT(A45,"yyyy-mm") | E45: 2.1017 | F45: 2.1019 | G45: 2.117 | H45: 2.1496 | I45: 2.1292 | T45: =IFERROR(AVERAGE(D45:S45),"")
A46: 43710 | B46: 43714 | C46: =TEXT(A46,"yyyy-mm") | D46: 2.121583 | E46: 2.150355 | F46: 2.124083 | G46: 2.138208 | H46: 2.17777 | I46: 2.16871 | J46: 2.158145 | K46: 2.180343 | L46: 2.243228 | M46: 2.250268 | N46: 2.186418 | O46: 2.203838 | P46: 2.211238 | Q46: 2.208998 | R46: 2.18728 | S46: 2.177495 | T46: =IFERROR(AVERAGE(D46:S46),"")
A47: 43717 | B47: 43721 | C47: =TEXT(A47,"yyyy-mm") | D47: 2.14897 | E47: 2.175732 | F47: 2.150292 | G47: 2.163554 | H47: 2.20195 | I47: 2.192758 | J47: 2.182396 | K47: 2.206552 | L47: 2.26741 | M47: 2.274444 | N47: 2.2106 | O47: 2.228014 | P47: 2.235414 | Q47: 2.233174 | R47: 2.211326 | S47: 2.201746 | T47: =IFERROR(AVERAGE(D47:S47),"")
A48: 43724 | B48: 43728 | C48: =TEXT(A48,"yyyy-mm") | D48: 2.248426 | E48: 2.274384 | F48: 2.249206 | G48: 2.26216 | H48: 2.300102 | I48: 2.290974 | J48: 2.280426 | K48: 2.305466 | L48: 2.365556 | M48: 2.372594 | N48: 2.308746 | O48: 2.326164 | P48: 2.333564 | Q48: 2.331324 | R48: 2.309544 | S48: 2.299778 | T48: =IFERROR(AVERAGE(D48:S48),"")
A49: 43731 | B49: 43735 | C49: =TEXT(A49,"yyyy-mm") | D49: 2.261728 | E49: 2.287338 | F49: 2.262198 | G49: 2.275128 | H49: 2.313048 | I49: 2.303872 | J49: 2.293434 | K49: 2.318458 | L49: 2.378508 | M49: 2.38554 | N49: 2.321698 | O49: 2.33911 | P49: 2.34651 | Q49: 2.34427 | R49: 2.322442 | S49: 2.312784 | T49: =IFERROR(AVERAGE(D49:S49),"")
A50: 43738 | B50: 43742 | C50: =TEXT(A50,"yyyy-mm") | D50: 2.172308 | E50: 2.199202 | F50: 2.17364 | G50: 2.187026 | H50: 2.225588 | I50: 2.216426 | J50: 2.206008 | K50: 2.229902 | L50: 2.291046 | M50: 2.298082 | N50: 2.234234 | O50: 2.251652 | P50: 2.259052 | Q50: 2.256812 | R50: 2.234992 | S50: 2.225358 | T50: =IFERROR(AVERAGE(D50:S50),"")
A51: 43745 | B51: 43749 | C51: =TEXT(A51,"yyyy-mm") | D51: 2.191178 | E51: 2.22524 | F51: 2.196996 | G51: 2.213122 | H51: 2.255326 | I51: 2.24673 | J51: 2.235334 | K51: 2.253256 | L51: 2.320784 | M51: 2.327822 | N51: 2.263974 | O51: 2.281392 | P51: 2.288792 | Q51: 2.286552 | R51: 2.265298 | S51: 2.254686 | T51: =IFERROR(AVERAGE(D51:S51),"")
A52: 43752 | B52: 43756 | C52: =TEXT(A52,"yyyy-mm") | D52: 2.22614 | E52: 2.26689 | F52: 2.235992 | G52: 2.254896 | H52: 2.300884 | I52: 2.292624 | J52: 2.280776 | K52: 2.292254 | L52: 2.36634 | M52: 2.373378 | N52: 2.30953 | O52: 2.326948 | P52: 2.334348 | Q52: 2.332108 | R52: 2.311192 | S52: 2.300126 | T52: =IFERROR(AVERAGE(D52:S52),"")
A53: 43759 | B53: 43763 | C53: =TEXT(A53,"yyyy-mm") | D53: 2.177342 | E53: 2.213266 | F53: 2.184396 | G53: 2.201132 | H53: 2.244116 | I53: 2.235736 | J53: 2.223916 | K53: 2.240656 | L53: 2.309574 | M53: 2.316606 | N53: 2.252764 | O53: 2.270176 | P53: 2.277576 | Q53: 2.275336 | R53: 2.254302 | S53: 2.243268 | T53: =IFERROR(AVERAGE(D53:S53),"")
A54: 43766 | B54: 43770 | C54: =TEXT(A54,"yyyy-mm") | D54: 2.111622 | E54: 2.146162 | F54: 2.117916 | G54: 2.13401 | H54: 2.176122 | I54: 2.167636 | J54: 2.155986 | K54: 2.17418 | L54: 2.241582 | M54: 2.248616 | N54: 2.184772 | O54: 2.202184 | P54: 2.209584 | Q54: 2.207344 | R54: 2.186204 | S54: 2.175338 | T54: =IFERROR(AVERAGE(D54:S54),"")
A55: 43773 | B55: 43777 | C55: =TEXT(A55,"yyyy-mm") | D55: 2.147288 | E55: 2.189224 | F55: 2.158068 | G55: 2.177148 | H55: 2.223252 | I55: 2.215338 | J55: 2.202734 | K55: 2.21433 | L55: 2.288712 | M55: 2.295748 | N55: 2.231902 | O55: 2.249318 | P55: 2.256718 | Q55: 2.254478 | R55: 2.233902 | S55: 2.222084 | T55: =IFERROR(AVERAGE(D55:S55),"")
A56: 43780 | B56: 43784 | C56: =TEXT(A56,"yyyy-mm") | D56: 2.181572 | E56: 2.226402 | F56: 2.193906 | G56: 2.214444 | H56: 2.26261 | I56: 2.254682 | J56: 2.242258 | K56: 2.250168 | L56: 2.328064 | M56: 2.335102 | N56: 2.271254 | O56: 2.288672 | P56: 2.296072 | Q56: 2.293832 | R56: 2.273248 | S56: 2.261608 | T56: =IFERROR(AVERAGE(D56:S56),"")
A57: 43787 | B57: 43791 | C57: =TEXT(A57,"yyyy-mm") | D57: 2.18088 | E57: 2.224066 | F57: 2.192146 | G57: 2.212112 | H57: 2.25954 | I57: 2.251436 | J57: 2.239354 | K57: 2.248406 | L57: 2.324998 | M57: 2.332036 | N57: 2.268188 | O57: 2.285606 | P57: 2.293004 | Q57: 2.290764 | R57: 2.27 | S57: 2.258704 | T57: =IFERROR(AVERAGE(D57:S57),"")
... A414: 46286 | B414: 46290 | C414: =TEXT(A414,"yyyy-mm") | D414: 6.628382 | E414: 6.577578 | F414: 6.525512 | G414: 6.567578 | H414: 6.574984 | I414: 6.580022 | J414: 6.564636 | K414: 6.680018 | L414: 6.754302 | M414: 6.776 | N414: 6.609312 | O414: 6.626946 | P414: 6.672764 | Q414: 6.656328 | R414: 6.640014 | S414: 6.625644 | T414: =IFERROR(AVERAGE(D414:S414),"")
A416: Fonte: ANP, PPI (S&P Global Commodity Insights / Abicom-StoneX) — download oficial, 412 semanas, 2018-11-05 a 2026-09-21.

Sheet PPI ANP - Gasolina (semanal)
A1: PPI oficial ANP — Gasolina (semanal) — médio semanal por polo (R$/litro, sem tributos)
A2: Semana início | B2: Semana fim | C2: AnoMes | D2: Manaus | E2: Itaqui | F2: Suape | G2: Aratu | H2: Santos | I2: Paranagua | J2: Tramandai | K2: Guamare | L2: Duque de Caxias | M2: Betim | N2: Cubatao | O2: Maua | P2: Paulinia | Q2: Sao Jose dos Campos | R2: Araucaria | S2: Canoas | T2: Média simples (aprox. nacional)
A3: 43409 | B3: 43413 | C3: =TEXT(A3,"yyyy-mm") | E3: 1.602604 | F3: 1.616238 | G3: 1.617774 | H3: 1.653378 | I3: 1.630454 | T3: =IFERROR(AVERAGE(D3:S3),"")
A4: 43416 | B4: 43420 | C4: =TEXT(A4,"yyyy-mm") | E4: 1.524086 | F4: 1.537714 | G4: 1.539262 | H4: 1.574876 | I4: 1.551936 | T4: =IFERROR(AVERAGE(D4:S4),"")
A5: 43423 | B5: 43427 | C5: =TEXT(A5,"yyyy-mm") | E5: 1.48227 | F5: 1.4958967 | G5: 1.4974433 | H5: 1.5368167 | I5: 1.51405 | T5: =IFERROR(AVERAGE(D5:S5),"")
A6: 43430 | B6: 43434 | C6: =TEXT(A6,"yyyy-mm") | E6: 1.40253 | F6: 1.416134 | G6: 1.417722 | H6: 1.458436 | I6: 1.435668 | T6: =IFERROR(AVERAGE(D6:S6),"")
A7: 43437 | B7: 43441 | C7: =TEXT(A7,"yyyy-mm") | E7: 1.4132 | F7: 1.4268 | G7: 1.4284 | H7: 1.4754 | I7: 1.4529 | T7: =IFERROR(AVERAGE(D7:S7),"")
A8: 43444 | B8: 43448 | C8: =TEXT(A8,"yyyy-mm") | E8: 1.4263 | F8: 1.44 | G8: 1.4415 | H8: 1.4892 | I8: 1.4667 | T8: =IFERROR(AVERAGE(D8:S8),"")
A9: 43451 | B9: 43455 | C9: =TEXT(A9,"yyyy-mm") | E9: 1.354148 | F9: 1.367754 | G9: 1.369344 | H9: 1.40937 | I9: 1.386564 | T9: =IFERROR(AVERAGE(D9:S9),"")
A10: 43458 | B10: 43462 | C10: =TEXT(A10,"yyyy-mm") | E10: 1.2728527 | F10: 1.2957005 | G10: 1.3033279 | H10: 1.3239864 | I10: 1.304272 | T10: =IFERROR(AVERAGE(D10:S10),"")
A11: 43465 | B11: 43469 | C11: =TEXT(A11,"yyyy-mm") | E11: 1.2621067 | F11: 1.2758267 | G11: 1.2771867 | H11: 1.3119133 | I11: 1.2892533 | T11: =IFERROR(AVERAGE(D11:S11),"")
A12: 43472 | B12: 43476 | C12: =TEXT(A12,"yyyy-mm") | E12: 1.291026 | F12: 1.304758 | G12: 1.306098 | H12: 1.33958 | I12: 1.316866 | T12: =IFERROR(AVERAGE(D12:S12),"")
A13: 43479 | B13: 43483 | C13: =TEXT(A13,"yyyy-mm") | E13: 1.344538 | F13: 1.358272 | G13: 1.359602 | H13: 1.390746 | I13: 1.367942 | T13: =IFERROR(AVERAGE(D13:S13),"")
A14: 43486 | B14: 43490 | C14: =TEXT(A14,"yyyy-mm") | E14: 1.3735075 | F14: 1.3872425 | G14: 1.3885725 | H14: 1.418995 | I14: 1.3961525 | T14: =IFERROR(AVERAGE(D14:S14),"")
... A45: 43703 | B45: 43707 | C45: =TEXT(A45,"yyyy-mm") | E45: 1.556 | F45: 1.5697 | G45: 1.5712 | H45: 1.6068 | I45: 1.5837 | T45: =IFERROR(AVERAGE(D45:S45),"")
A46: 43710 | B46: 43714 | C46: =TEXT(A46,"yyyy-mm") | D46: 1.56833 | E46: 1.58206 | F46: 1.56833 | G46: 1.569793 | H46: 1.612183 | I46: 1.600593 | J46: 1.59458 | K46: 1.624593 | L46: 1.67764 | M46: 1.684678 | N46: 1.62083 | O46: 1.638248 | P46: 1.645648 | Q46: 1.643408 | R46: 1.619163 | S46: 1.61393 | T46: =IFERROR(AVERAGE(D46:S46),"")
A47: 43717 | B47: 43721 | C47: =TEXT(A47,"yyyy-mm") | D47: 1.598412 | E47: 1.612116 | F47: 1.598412 | G47: 1.599816 | H47: 1.64085 | I47: 1.6293 | J47: 1.623172 | K47: 1.654672 | L47: 1.706304 | M47: 1.713344 | N47: 1.649494 | O47: 1.666914 | P47: 1.674314 | Q47: 1.672074 | R47: 1.647868 | S47: 1.642522 | T47: =IFERROR(AVERAGE(D47:S47),"")
A48: 43724 | B48: 43728 | C48: =TEXT(A48,"yyyy-mm") | D48: 1.696246 | E48: 1.709912 | F48: 1.696246 | G48: 1.697578 | H48: 1.738114 | I48: 1.726666 | J48: 1.720304 | K48: 1.752506 | L48: 1.803574 | M48: 1.810608 | N48: 1.746764 | O48: 1.764178 | P48: 1.771578 | Q48: 1.769338 | R48: 1.745232 | S48: 1.739654 | T48: =IFERROR(AVERAGE(D48:S48),"")
A49: 43731 | B49: 43735 | C49: =TEXT(A49,"yyyy-mm") | D49: 1.701888 | E49: 1.715564 | F49: 1.701888 | G49: 1.703242 | H49: 1.743742 | I49: 1.732258 | J49: 1.72597 | K49: 1.75815 | L49: 1.809198 | M49: 1.816236 | N49: 1.752388 | O49: 1.769804 | P49: 1.777204 | Q49: 1.774964 | R49: 1.750826 | S49: 1.745322 | T49: =IFERROR(AVERAGE(D49:S49),"")
A50: 43738 | B50: 43742 | C50: =TEXT(A50,"yyyy-mm") | D50: 1.621876 | E50: 1.63558 | F50: 1.621876 | G50: 1.623282 | H50: 1.664508 | I50: 1.65296 | J50: 1.646832 | K50: 1.678136 | L50: 1.729966 | M50: 1.737 | N50: 1.673156 | O50: 1.69057 | P50: 1.69797 | Q50: 1.69573 | R50: 1.67153 | S50: 1.666182 | T50: =IFERROR(AVERAGE(D50:S50),"")
A51: 43745 | B51: 43749 | C51: =TEXT(A51,"yyyy-mm") | D51: 1.640566 | E51: 1.65432 | F51: 1.640566 | G51: 1.642072 | H51: 1.687612 | I51: 1.676044 | J51: 1.670026 | K51: 1.696826 | L51: 1.75307 | M51: 1.760106 | N51: 1.69626 | O51: 1.713674 | P51: 1.721074 | Q51: 1.718834 | R51: 1.69461 | S51: 1.689376 | T51: =IFERROR(AVERAGE(D51:S51),"")
A52: 43752 | B52: 43756 | C52: =TEXT(A52,"yyyy-mm") | D52: 1.727456 | E52: 1.741316 | F52: 1.727456 | G52: 1.729178 | H52: 1.779102 | I52: 1.767336 | J52: 1.761838 | K52: 1.783718 | L52: 1.844562 | M52: 1.8516 | N52: 1.787752 | O52: 1.805168 | P52: 1.812568 | Q52: 1.810328 | R52: 1.785904 | S52: 1.781188 | T52: =IFERROR(AVERAGE(D52:S52),"")
A53: 43759 | B53: 43763 | C53: =TEXT(A53,"yyyy-mm") | D53: 1.7074 | E53: 1.721144 | F53: 1.7074 | G53: 1.708884 | H53: 1.755378 | I53: 1.743872 | J53: 1.73772 | K53: 1.76366 | L53: 1.820836 | M53: 1.827872 | N53: 1.764026 | O53: 1.781442 | P53: 1.788842 | Q53: 1.786602 | R53: 1.762438 | S53: 1.757072 | T53: =IFERROR(AVERAGE(D53:S53),"")
A54: 43766 | B54: 43770 | C54: =TEXT(A54,"yyyy-mm") | D54: 1.711706 | E54: 1.725428 | F54: 1.711706 | G54: 1.713156 | H54: 1.758632 | I54: 1.747152 | J54: 1.740928 | K54: 1.767968 | L54: 1.824086 | M54: 1.831124 | N54: 1.767276 | O54: 1.784694 | P54: 1.792094 | Q54: 1.789854 | R54: 1.765718 | S54: 1.760278 | T54: =IFERROR(AVERAGE(D54:S54),"")
A55: 43773 | B55: 43777 | C55: =TEXT(A55,"yyyy-mm") | D55: 1.749092 | E55: 1.762884 | F55: 1.749092 | G55: 1.750674 | H55: 1.800856 | I55: 1.789316 | J55: 1.783294 | K55: 1.805352 | L55: 1.86631 | M55: 1.87335 | N55: 1.8095 | O55: 1.82692 | P55: 1.83432 | Q55: 1.83208 | R55: 1.80788 | S55: 1.802648 | T55: =IFERROR(AVERAGE(D55:S55),"")
A56: 43780 | B56: 43784 | C56: =TEXT(A56,"yyyy-mm") | D56: 1.781404 | E56: 1.795294 | F56: 1.781404 | G56: 1.783188 | H56: 1.835686 | I56: 1.8239 | J56: 1.818476 | K56: 1.837664 | L56: 1.901146 | M56: 1.908178 | N56: 1.844336 | O56: 1.861748 | P56: 1.869148 | Q56: 1.866908 | R56: 1.84247 | S56: 1.837828 | T56: =IFERROR(AVERAGE(D56:S56),"")
A57: 43787 | B57: 43791 | C57: =TEXT(A57,"yyyy-mm") | D57: 1.81702 | E57: 1.830916 | F57: 1.81702 | G57: 1.818812 | H57: 1.870416 | I57: 1.858592 | J57: 1.853248 | K57: 1.87328 | L57: 1.935876 | M57: 1.94291 | N57: 1.879064 | O57: 1.896478 | P57: 1.903878 | Q57: 1.901638 | R57: 1.877158 | S57: 1.872598 | T57: =IFERROR(AVERAGE(D57:S57),"")
... A414: 46286 | B414: 46290 | C414: =TEXT(A414,"yyyy-mm") | D414: 3.799536 | E414: 3.80314 | F414: 3.781106 | G414: 3.79314 | H414: 3.798294 | I414: 3.789244 | J414: 3.79668 | K414: 3.935612 | L414: 3.977612 | M414: 3.999306 | N414: 3.832622 | O414: 3.850254 | P414: 3.89607 | Q414: 3.879638 | R414: 3.849234 | S414: 3.857688 | T414: =IFERROR(AVERAGE(D414:S414),"")
A416: Fonte: ANP, PPI (S&P Global Commodity Insights / Abicom-StoneX) — download oficial, 412 semanas, 2018-11-05 a 2026-09-21.

Sheet Preço Realização (semanal)
A1: Preço de realização — ANP, preço médio ponderado semanal praticado pelas refinarias, Brasil, sem ICMS (R$/litro) | F1: Preço de realização — Gasolina A Comum, Brasil, sem ICMS (R$/litro)
A2: Semana início | B2: Semana fim | C2: AnoMes | D2: Diesel Brasil (R$/L) | F2: Semana início | G2: Semana fim | H2: AnoMes | I2: Gasolina Brasil (R$/L)
A3: 42373 | B3: 42379 | C3: =TEXT(A3,"yyyy-mm") | D3: 2.06353 | F3: 42373 | G3: 42379 | H3: =TEXT(F3,"yyyy-mm") | I3: 2.01747
A4: 42380 | B4: 42386 | C4: =TEXT(A4,"yyyy-mm") | D4: 2.05869 | F4: 42380 | G4: 42386 | H4: =TEXT(F4,"yyyy-mm") | I4: 2.01893
A5: 42387 | B5: 42393 | C5: =TEXT(A5,"yyyy-mm") | D5: 2.06129 | F5: 42387 | G5: 42393 | H5: =TEXT(F5,"yyyy-mm") | I5: 2.01517
A6: 42394 | B6: 42400 | C6: =TEXT(A6,"yyyy-mm") | D6: 2.06188 | F6: 42394 | G6: 42400 | H6: =TEXT(F6,"yyyy-mm") | I6: 2.01819
A7: 42401 | B7: 42407 | C7: =TEXT(A7,"yyyy-mm") | D7: 2.05695 | F7: 42401 | G7: 42407 | H7: =TEXT(F7,"yyyy-mm") | I7: 2.01971
A8: 42408 | B8: 42414 | C8: =TEXT(A8,"yyyy-mm") | D8: 2.06299 | F8: 42408 | G8: 42414 | H8: =TEXT(F8,"yyyy-mm") | I8: 2.02889
A9: 42415 | B9: 42421 | C9: =TEXT(A9,"yyyy-mm") | D9: 2.06673 | F9: 42415 | G9: 42421 | H9: =TEXT(F9,"yyyy-mm") | I9: 2.02598
A10: 42422 | B10: 42428 | C10: =TEXT(A10,"yyyy-mm") | D10: 2.06216 | F10: 42422 | G10: 42428 | H10: =TEXT(F10,"yyyy-mm") | I10: 2.02991
A11: 42429 | B11: 42435 | C11: =TEXT(A11,"yyyy-mm") | D11: 2.06036 | F11: 42429 | G11: 42435 | H11: =TEXT(F11,"yyyy-mm") | I11: 2.01838
A12: 42436 | B12: 42442 | C12: =TEXT(A12,"yyyy-mm") | D12: 2.06421 | F12: 42436 | G12: 42442 | H12: =TEXT(F12,"yyyy-mm") | I12: 2.02461
A13: 42443 | B13: 42449 | C13: =TEXT(A13,"yyyy-mm") | D13: 2.05856 | F13: 42443 | G13: 42449 | H13: =TEXT(F13,"yyyy-mm") | I13: 2.02639
A14: 42450 | B14: 42456 | C14: =TEXT(A14,"yyyy-mm") | D14: 2.05978 | F14: 42450 | G14: 42456 | H14: =TEXT(F14,"yyyy-mm") | I14: 2.02542
... A558: 46279 | B558: 46285 | C558: =TEXT(A558,"yyyy-mm") | D558: 3.88156 | F558: 46258 | G558: 46264 | H558: =TEXT(F558,"yyyy-mm") | I558: 3.79507
F559: 46265 | G559: 46271 | H559: =TEXT(F559,"yyyy-mm") | I559: 3.87763
F560: 46272 | G560: 46278 | H560: =TEXT(F560,"yyyy-mm") | I560: 3.5446
F561: 46279 | G561: 46285 | H561: =TEXT(F561,"yyyy-mm") | I561: 3.45615
A563: Fonte: ANP, Preços Médios Ponderados Semanais Praticados por Produtores e Importadores — download oficial. Diesel: 556 semanas (2016-01-04 a 2026-09-14). Gasolina: 559 semanas (2016-01-04 a 2026-09-14).

Sheet Defasagem Histórica (mensal)
A1: Defasagem histórica mensal — PPI (ANP) vs. Preço de Realização (ANP), Diesel e Gasolina
A2: PPI = média simples entre polos (aproximação nacional). Ambas as séries são sem tributos. nov/2018–ago/2023 = vigência da política oficial de PPI da Petrobras; a partir de set/2023 a defasagem passa a ser lida como "vs. paridade de mercado", já que a Petrobras não usa mais o PPI como política declarada desde 16/05/2023.
A4: Mês | B4: PPI Diesel (R$/L) | C4: Realização Diesel (R$/L) | D4: Defasagem Diesel (%) | E4: PPI Gasolina (R$/L) | F4: Realização Gasolina (R$/L) | G4: Defasagem Gasolina (%)
A5: 2018-11 | B5: =IFERROR(AVERAGEIF('PPI ANP - Diesel (semanal)'!$C:$C,$A5,'PPI ANP - Diesel (semanal)'!$T:$T),"") | C5: =IFERROR(AVERAGEIF('Preço Realização (semanal)'!$C:$C,$A5,'Preço Realização (semanal)'!$D:$D),"") | D5: =IF(OR(B5="",C5=""),"",(B5-C5)/B5) | E5: =IFERROR(AVERAGEIF('PPI ANP - Gasolina (semanal)'!$C:$C,$A5,'PPI ANP - Gasolina (semanal)'!$T:$T),"") | F5: =IFERROR(AVERAGEIF('Preço Realização (semanal)'!$H:$H,$A5,'Preço Realização (semanal)'!$I:$I),"") | G5: =IF(OR(E5="",F5=""),"",(E5-F5)/E5)
A6: 2018-12 | B6: =IFERROR(AVERAGEIF('PPI ANP - Diesel (semanal)'!$C:$C,$A6,'PPI ANP - Diesel (semanal)'!$T:$T),"") | C6: =IFERROR(AVERAGEIF('Preço Realização (semanal)'!$C:$C,$A6,'Preço Realização (semanal)'!$D:$D),"") | D6: =IF(OR(B6="",C6=""),"",(B6-C6)/B6) | E6: =IFERROR(AVERAGEIF('PPI ANP - Gasolina (semanal)'!$C:$C,$A6,'PPI ANP - Gasolina (semanal)'!$T:$T),"") | F6: =IFERROR(AVERAGEIF('Preço Realização (semanal)'!$H:$H,$A6,'Preço Realização (semanal)'!$I:$I),"") | G6: =IF(OR(E6="",F6=""),"",(E6-F6)/E6)
A7: 2019-01 | B7: =IFERROR(AVERAGEIF('PPI ANP - Diesel (semanal)'!$C:$C,$A7,'PPI ANP - Diesel (semanal)'!$T:$T),"") | C7: =IFERROR(AVERAGEIF('Preço Realização (semanal)'!$C:$C,$A7,'Preço Realização (semanal)'!$D:$D),"") | D7: =IF(OR(B7="",C7=""),"",(B7-C7)/B7) | E7: =IFERROR(AVERAGEIF('PPI ANP - Gasolina (semanal)'!$C:$C,$A7,'PPI ANP - Gasolina (semanal)'!$T:$T),"") | F7: =IFERROR(AVERAGEIF('Preço Realização (semanal)'!$H:$H,$A7,'Preço Realização (semanal)'!$I:$I),"") | G7: =IF(OR(E7="",F7=""),"",(E7-F7)/E7)
A8: 2019-02 | B8: =IFERROR(AVERAGEIF('PPI ANP - Diesel (semanal)'!$C:$C,$A8,'PPI ANP - Diesel (semanal)'!$T:$T),"") | C8: =IFERROR(AVERAGEIF('Preço Realização (semanal)'!$C:$C,$A8,'Preço Realização (semanal)'!$D:$D),"") | D8: =IF(OR(B8="",C8=""),"",(B8-C8)/B8) | E8: =IFERROR(AVERAGEIF('PPI ANP - Gasolina (semanal)'!$C:$C,$A8,'PPI ANP - Gasolina (semanal)'!$T:$T),"") | F8: =IFERROR(AVERAGEIF('Preço Realização (semanal)'!$H:$H,$A8,'Preço Realização (semanal)'!$I:$I),"") | G8: =IF(OR(E8="",F8=""),"",(E8-F8)/E8)
A9: 2019-03 | B9: =IFERROR(AVERAGEIF('PPI ANP - Diesel (semanal)'!$C:$C,$A9,'PPI ANP - Diesel (semanal)'!$T:$T),"") | C9: =IFERROR(AVERAGEIF('Preço Realização (semanal)'!$C:$C,$A9,'Preço Realização (semanal)'!$D:$D),"") | D9: =IF(OR(B9="",C9=""),"",(B9-C9)/B9) | E9: =IFERROR(AVERAGEIF('PPI ANP - Gasolina (semanal)'!$C:$C,$A9,'PPI ANP - Gasolina (semanal)'!$T:$T),"") | F9: =IFERROR(AVERAGEIF('Preço Realização (semanal)'!$H:$H,$A9,'Preço Realização (semanal)'!$I:$I),"") | G9: =IF(OR(E9="",F9=""),"",(E9-F9)/E9)
A10: 2019-04 | B10: =IFERROR(AVERAGEIF('PPI ANP - Diesel (semanal)'!$C:$C,$A10,'PPI ANP - Diesel (semanal)'!$T:$T),"") | C10: =IFERROR(AVERAGEIF('Preço Realização (semanal)'!$C:$C,$A10,'Preço Realização (semanal)'!$D:$D),"") | D10: =IF(OR(B10="",C10=""),"",(B10-C10)/B10) | E10: =IFERROR(AVERAGEIF('PPI ANP - Gasolina (semanal)'!$C:$C,$A10,'PPI ANP - Gasolina (semanal)'!$T:$T),"") | F10: =IFERROR(AVERAGEIF('Preço Realização (semanal)'!$H:$H,$A10,'Preço Realização (semanal)'!$I:$I),"") | G10: =IF(OR(E10="",F10=""),"",(E10-F10)/E10)
A11: 2019-05 | B11: =IFERROR(AVERAGEIF('PPI ANP - Diesel (semanal)'!$C:$C,$A11,'PPI ANP - Diesel (semanal)'!$T:$T),"") | C11: =IFERROR(AVERAGEIF('Preço Realização (semanal)'!$C:$C,$A11,'Preço Realização (semanal)'!$D:$D),"") | D11: =IF(OR(B11="",C11=""),"",(B11-C11)/B11) | E11: =IFERROR(AVERAGEIF('PPI ANP - Gasolina (semanal)'!$C:$C,$A11,'PPI ANP - Gasolina (semanal)'!$T:$T),"") | F11: =IFERROR(AVERAGEIF('Preço Realização (semanal)'!$H:$H,$A11,'Preço Realização (semanal)'!$I:$I),"") | G11: =IF(OR(E11="",F11=""),"",(E11-F11)/E11)
A12: 2019-06 | B12: =IFERROR(AVERAGEIF('PPI ANP - Diesel (semanal)'!$C:$C,$A12,'PPI ANP - Diesel (semanal)'!$T:$T),"") | C12: =IFERROR(AVERAGEIF('Preço Realização (semanal)'!$C:$C,$A12,'Preço Realização (semanal)'!$D:$D),"") | D12: =IF(OR(B12="",C12=""),"",(B12-C12)/B12) | E12: =IFERROR(AVERAGEIF('PPI ANP - Gasolina (semanal)'!$C:$C,$A12,'PPI ANP - Gasolina (semanal)'!$T:$T),"") | F12: =IFERROR(AVERAGEIF('Preço Realização (semanal)'!$H:$H,$A12,'Preço Realização (semanal)'!$I:$I),"") | G12: =IF(OR(E12="",F12=""),"",(E12-F12)/E12)
A13: 2019-07 | B13: =IFERROR(AVERAGEIF('PPI ANP - Diesel (semanal)'!$C:$C,$A13,'PPI ANP - Diesel (semanal)'!$T:$T),"") | C13: =IFERROR(AVERAGEIF('Preço Realização (semanal)'!$C:$C,$A13,'Preço Realização (semanal)'!$D:$D),"") | D13: =IF(OR(B13="",C13=""),"",(B13-C13)/B13) | E13: =IFERROR(AVERAGEIF('PPI ANP - Gasolina (semanal)'!$C:$C,$A13,'PPI ANP - Gasolina (semanal)'!$T:$T),"") | F13: =IFERROR(AVERAGEIF('Preço Realização (semanal)'!$H:$H,$A13,'Preço Realização (semanal)'!$I:$I),"") | G13: =IF(OR(E13="",F13=""),"",(E13-F13)/E13)
A14: 2019-08 | B14: =IFERROR(AVERAGEIF('PPI ANP - Diesel (semanal)'!$C:$C,$A14,'PPI ANP - Diesel (semanal)'!$T:$T),"") | C14: =IFERROR(AVERAGEIF('Preço Realização (semanal)'!$C:$C,$A14,'Preço Realização (semanal)'!$D:$D),"") | D14: =IF(OR(B14="",C14=""),"",(B14-C14)/B14) | E14: =IFERROR(AVERAGEIF('PPI ANP - Gasolina (semanal)'!$C:$C,$A14,'PPI ANP - Gasolina (semanal)'!$T:$T),"") | F14: =IFERROR(AVERAGEIF('Preço Realização (semanal)'!$H:$H,$A14,'Preço Realização (semanal)'!$I:$I),"") | G14: =IF(OR(E14="",F14=""),"",(E14-F14)/E14)
A15: 2019-09 | B15: =IFERROR(AVERAGEIF('PPI ANP - Diesel (semanal)'!$C:$C,$A15,'PPI ANP - Diesel (semanal)'!$T:$T),"") | C15: =IFERROR(AVERAGEIF('Preço Realização (semanal)'!$C:$C,$A15,'Preço Realização (semanal)'!$D:$D),"") | D15: =IF(OR(B15="",C15=""),"",(B15-C15)/B15) | E15: =IFERROR(AVERAGEIF('PPI ANP - Gasolina (semanal)'!$C:$C,$A15,'PPI ANP - Gasolina (semanal)'!$T:$T),"") | F15: =IFERROR(AVERAGEIF('Preço Realização (semanal)'!$H:$H,$A15,'Preço Realização (semanal)'!$I:$I),"") | G15: =IF(OR(E15="",F15=""),"",(E15-F15)/E15)
A16: 2019-10 | B16: =IFERROR(AVERAGEIF('PPI ANP - Diesel (semanal)'!$C:$C,$A16,'PPI ANP - Diesel (semanal)'!$T:$T),"") | C16: =IFERROR(AVERAGEIF('Preço Realização (semanal)'!$C:$C,$A16,'Preço Realização (semanal)'!$D:$D),"") | D16: =IF(OR(B16="",C16=""),"",(B16-C16)/B16) | E16: =IFERROR(AVERAGEIF('PPI ANP - Gasolina (semanal)'!$C:$C,$A16,'PPI ANP - Gasolina (semanal)'!$T:$T),"") | F16: =IFERROR(AVERAGEIF('Preço Realização (semanal)'!$H:$H,$A16,'Preço Realização (semanal)'!$I:$I),"") | G16: =IF(OR(E16="",F16=""),"",(E16-F16)/E16)
... A99: 2026-09 | B99: =IFERROR(AVERAGEIF('PPI ANP - Diesel (semanal)'!$C:$C,$A99,'PPI ANP - Diesel (semanal)'!$T:$T),"") | C99: =IFERROR(AVERAGEIF('Preço Realização (semanal)'!$C:$C,$A99,'Preço Realização (semanal)'!$D:$D),"") | D99: =IF(OR(B99="",C99=""),"",(B99-C99)/B99) | E99: =IFERROR(AVERAGEIF('PPI ANP - Gasolina (semanal)'!$C:$C,$A99,'PPI ANP - Gasolina (semanal)'!$T:$T),"") | F99: =IFERROR(AVERAGEIF('Preço Realização (semanal)'!$H:$H,$A99,'Preço Realização (semanal)'!$I:$I),"") | G99: =IF(OR(E99="",F99=""),"",(E99-F99)/E99)

Sheet Fontes
A1: Fontes e metodologia
A3: Dado | B3: Fonte | C3: URL | D3: Cobertura / data de extração
A4: Brent (US$/bbl, mensal) | B4: EIA, via FRED — série MCOILBRENTEU | C4: https://fred.stlouisfed.org/series/MCOILBRENTEU | D4: jan/2016–ago/2026 · extraído 28/09/2026
A5: Câmbio USD/BRL (venda, mensal) | B5: Banco Central do Brasil — SGS série 3695 | C5: https://api.bcb.gov.br/dados/serie/bcdata.sgs.3695/dados?formato=json | D5: jan/2016–ago/2026 · extraído 28/09/2026
A6: PPI oficial (diesel e gasolina, semanal, por polo) | B6: ANP — metodologia S&P Global Commodity Insights / Abicom-StoneX | C6: https://www.gov.br/anp/pt-br/assuntos/precos-e-defesa-da-concorrencia/precos/arq-ppi/ppi.xlsx | D6: nov/2018–21/09/2026 · baixado 28/09/2026
A7: Preço de realização (produtor/importador, semanal, Brasil sem ICMS) | B7: ANP — Preços Médios Ponderados Semanais | C7: https://www.gov.br/anp/pt-br/assuntos/precos-e-defesa-da-concorrencia/precos/ppidp/precos-medios-ponderados-semanais-2013.xls | D7: jan/2016–14/09/2026 (arquivo cobre desde 2013) · baixado 28/09/2026
A8: Fim da política de PPI da Petrobras (16/05/2023) | B8: Cobertura de imprensa do anúncio oficial da Petrobras | C8: — | D8: confirmado por múltiplas fontes de imprensa; ver texto na aba Leia-me
A9: Metodologia detalhada do PPI (frete, margem, tributos linha a linha) | B9: Abicom — Relatórios do PPI (acesso restrito/cadastro) | C9: https://abicom.com.br/ppi/ | D9: NÃO acessível publicamente — não incluído na calculadora por falta de confirmação
